README.md
setup.py
pulumi_threefold/__init__.py
pulumi_threefold/_inputs.py
pulumi_threefold/_utilities.py
pulumi_threefold/deployment.py
pulumi_threefold/gateway_fqdn.py
pulumi_threefold/gateway_name.py
pulumi_threefold/kubernetes.py
pulumi_threefold/network.py
pulumi_threefold/outputs.py
pulumi_threefold/provider.py
pulumi_threefold/pulumi-plugin.json
pulumi_threefold/py.typed
pulumi_threefold/scheduler.py
pulumi_threefold.egg-info/PKG-INFO
pulumi_threefold.egg-info/SOURCES.txt
pulumi_threefold.egg-info/dependency_links.txt
pulumi_threefold.egg-info/not-zip-safe
pulumi_threefold.egg-info/requires.txt
pulumi_threefold.egg-info/top_level.txt
pulumi_threefold/config/__init__.py
pulumi_threefold/config/vars.py