Metadata-Version: 2.1
Name: pulumi-threefold
Version: 0.8.1
Summary: The Pulumi Resource Provider for the Threefold Grid.
Home-page: https://www.pulumi.com
License: Apache-2.0
Project-URL: Repository, https://github.com/threefoldtech/pulumi-threefold
Keywords: pulumi grid threefold category/infrastructure kind/native
Requires-Python: >=3.8
